tergite/__init__.py
tergite/compat/__init__.py
tergite/compat/qiskit/__init__.py
tergite/compat/qiskit/assembler/__init__.py
tergite/compat/qiskit/assembler/assemble_circuits.py
tergite/compat/qiskit/assembler/assemble_schedules.py
tergite/compat/qiskit/assembler/disassemble.py
tergite/compat/qiskit/assembler/run_config.py
tergite/compat/qiskit/compiler/__init__.py
tergite/compat/qiskit/compiler/assembler.py
tergite/compat/qiskit/qobj/__init__.py
tergite/compat/qiskit/qobj/common.py
tergite/compat/qiskit/qobj/encoder.py
tergite/compat/qiskit/qobj/pulse_qobj.py
tergite/compat/qiskit/qobj/qasm_qobj.py
tergite/compat/qiskit/qobj/utils.py
tergite/compat/qiskit/qobj/converters/__init__.py
tergite/compat/qiskit/qobj/converters/lo_config.py
tergite/compat/qiskit/qobj/converters/pulse_instruction.py
tergite/services/__init__.py
tergite/services/api_client/__init__.py
tergite/services/api_client/dtos.py
tergite/services/configs/__init__.py
tergite/services/configs/dtos.py
tergite/services/device_compiler/__init__.py
tergite/services/device_compiler/functions.py
tergite/services/device_compiler/schedules.py
tergite/types/__init__.py
tergite/types/backend.py
tergite/types/job.py
tergite/types/provider.py
tergite/types/provider_factory.py
tergite/utils/__init__.py
tergite/utils/job_file.py
tergite/utils/qobj.py
tergite/utils/quantum_circuit.py
tergite-2025.9.0.dist-info/licenses/LICENSE.txt
tergite-2025.9.0.dist-info/METADATA
tergite-2025.9.0.dist-info/WHEEL
tergite-2025.9.0.dist-info/top_level.txt
tergite-2025.9.0.dist-info/RECORD
