Metadata-Version: 2.4
Name: tergite
Version: 2025.9.0
Summary: The SDK in the Tergite software stack for connecting to the Swedish quantum computer
Author: Miroslav Dobsicek, Axel Andersson, Martin Ahindura, Stefan Hill, Abdullah-al Amin, Adilet Tuleuov
Maintainer-email: Chalmers Next Labs AB <contact@quantum.chalmersnextlabs.se>
License: 
Project-URL: Homepage, https://github.com/tergite/tergite
Project-URL: Repository, https://github.com/tergite/tergite
Project-URL: Documentation, https://github.com/tergite/tergite
Project-URL: Issues, https://github.com/tergite/tergite/issues
Project-URL: Changelog, https://github.com/tergite/tergite/blob/main/CHANGELOG.md
Keywords: quantum-computer,qiskit,quantum,tergite,sdk
Classifier: Programming Language :: Python :: 3
Classifier: Operating System :: OS Independent
Requires-Python: >=3.12
License-File: LICENSE.txt
Requires-Dist: requests>=2.25.1
Requires-Dist: qiskit<1.3,>1
Requires-Dist: pandas>=1.4.2
Requires-Dist: numpy>=1.26.0
Requires-Dist: qiskit-ibm-runtime>=0.28.0
Requires-Dist: h5py>=3.8.0
Requires-Dist: pydantic>=2.5.0
Provides-Extra: test
Requires-Dist: pytest>=7.4.2; extra == "test"
Requires-Dist: requests-mock>=1.11.0; extra == "test"
Requires-Dist: scikit-learn~=1.7.0; extra == "test"
Provides-Extra: dev
Requires-Dist: jupyter>=1.0.0; extra == "dev"
Requires-Dist: python-dateutil>=2.8.1; extra == "dev"
Requires-Dist: python-multipart>=0.0.5; extra == "dev"
Requires-Dist: tqdm>=4.64.1; extra == "dev"
Requires-Dist: more-itertools>=8.14.0; extra == "dev"
Requires-Dist: matplotlib>=3.5.3; extra == "dev"
Requires-Dist: matplotlib-inline>=0.1.6; extra == "dev"
Requires-Dist: black[jupyter]~=25.1.0; extra == "dev"
Requires-Dist: isort~=6.0.1; extra == "dev"
Dynamic: license-file
